kananalyst/__init__.py
kananalyst-0.0.1.dist-info/License.txt
kananalyst-0.0.1.dist-info/METADATA
kananalyst-0.0.1.dist-info/WHEEL
kananalyst-0.0.1.dist-info/top_level.txt
kananalyst-0.0.1.dist-info/RECORD
