Metadata-Version: 2.1
Name: kananalyst
Version: 0.0.1
Summary: Allow easy querying of data from the PIARCHIVE Database. Return Information in various forms eg. Pivoted etc.
Author: Patiwa Danny Mhango
Author-email: patiwadannymhango@outlook.com
Classifier: Programming Language :: Python :: 3
Classifier: License :: OSI Approved :: MIT License
Classifier: Operating System :: OS Independent
License-File: License.txt
